<manifest alg="2" build="2017.0.0.363" opt="false" iceEnabled="true" iceMarkupVersion="2" iceEnabledOptions="link,responsive,cachebuster" exportTarget="other" domain="index.com" resolutions="1x" timestamp="1529816599481">
  <folder name="css">
    <file name="site_global.css" crc="443350757"/>
    <file name="master_a-master.css" crc="296616655" ref="index"/>
    <file name="nomq_preview_master_a-master.css" crc="3781105045" ref="index"/>
    <file name="index.css" crc="3878173103" ref="index"/>
    <file name="nomq_index.css" crc="4210573275" ref="index"/>
  </folder>
  <folder name="scripts">
    <file name="jquery-1.8.3.min.js" crc="209076791" ref="index"/>
    <file name="museutils.js" crc="163421577" ref="index"/>
    <file name="whatinput.js" crc="86476730" ref="index"/>
    <file name="museconfig.js" crc="168988563" ref="index"/>
    <file name="jquery.musemenu.js" crc="146495465" ref="index"/>
    <file name="jquery.watch.js" crc="104486786" ref="index"/>
    <file name="webpro.js" crc="3848665353" ref="index"/>
    <file name="form_check.php" crc="158155501" ref="index"/>
    <file name="form_throttle.php" crc="3992970984" ref="index"/>
    <file name="form_process.php" crc="4078697226" ref="index"/>
    <file name="form-u2500.php" crc="63070215" ref="index"/>
    <file name="html5shiv.js" crc="4241844378" ref="index"/>
    <file name="jquery.museresponsive.js" crc="4146931122" ref="index"/>
    <file name="require.js" crc="244322403" ref="index"/>
  </folder>
  <folder name="images">
    <file name="u102-4.png" crc="520257554" ref="index"/>
    <file name="u119-4.png" crc="524247270" ref="index"/>
    <file name="blank.gif" crc="4208392903" ref="index"/>
    <file name="magnifier-tool-crop-u2802.png" crc="74130330" ref="index"/>
    <file name="children-1822474-crop-u562.jpg" crc="3985838382" ref="index"/>
    <file name="u435-12.png" crc="69076739" ref="index"/>
    <file name="back-crop-u976.png" crc="191545622" ref="index"/>
    <file name="next-crop-u980.png" crc="3795480878" ref="index"/>
    <file name="books-1655783-crop-u638.jpg" crc="4202522758" ref="index"/>
    <file name="play-button-crop-u662.png" crc="3874367551" ref="index"/>
    <file name="u734-4.png" crc="518712940" ref="index"/>
    <file name="u738-4.png" crc="205912060" ref="index"/>
    <file name="books-2596809-crop-u1010.jpg" crc="428549158" ref="index"/>
    <file name="u1080-4.png" crc="408901386" ref="index"/>
    <file name="conference-crop-u1105.png" crc="3794169681" ref="index"/>
    <file name="u1121-6.png" crc="277340922" ref="index"/>
    <file name="u1125-4.png" crc="4240201973" ref="index"/>
    <file name="biology-crop-u1187.png" crc="3856618768" ref="index"/>
    <file name="u1185-6.png" crc="4080618028" ref="index"/>
    <file name="u1184-4.png" crc="4240201973" ref="index"/>
    <file name="lecture-crop-u1218.png" crc="3860442599" ref="index"/>
    <file name="u1220-6.png" crc="224652468" ref="index"/>
    <file name="u1216-4.png" crc="4240201973" ref="index"/>
    <file name="conference-crop-u1250.png" crc="3794169681" ref="index"/>
    <file name="u1252-6.png" crc="213950105" ref="index"/>
    <file name="u1248-4.png" crc="4240201973" ref="index"/>
    <file name="chalkboard-crop-u1641.jpg" crc="523867657" ref="index"/>
    <file name="people-2557396-crop-u1347.jpg" crc="331111273" ref="index"/>
    <file name="u1367-4.png" crc="319076073" ref="index"/>
    <file name="u1371-4.png" crc="313529296" ref="index"/>
    <file name="coffee-2306471-crop-u1530.jpg" crc="531105153" ref="index"/>
    <file name="u1535-4.png" crc="3932293582" ref="index"/>
    <file name="u1534-4.png" crc="4173930739" ref="index"/>
    <file name="library-849797-crop-u1582.jpg" crc="3857180614" ref="index"/>
    <file name="u1586-4.png" crc="4103088252" ref="index"/>
    <file name="u1585-4.png" crc="4173930739" ref="index"/>
    <file name="u1307-4.png" crc="267765322" ref="index"/>
    <file name="left-arrow-crop-u1669.png" crc="375845885" ref="index"/>
    <file name="right-arrow-crop-u1673.png" crc="3947871924" ref="index"/>
    <file name="knowledge-1052014-crop-u1788.jpg" crc="207228048" ref="index"/>
    <file name="u1808-4.png" crc="3845878218" ref="index"/>
    <file name="pexels-photo-428341-crop-u1890.jpg" crc="3804228041" ref="index"/>
    <file name="pexels-photo-220453-crop-u1906.jpg" crc="525449404" ref="index"/>
    <file name="official_portrait_of_elizabeth_truss_crop_2-crop-u1918.jpg" crc="86838660" ref="index"/>
    <file name="donald_pleasence_allan_warren_edit-crop-u1930.jpg" crc="3822950517" ref="index"/>
    <file name="u1978-4.png" crc="445635109" ref="index"/>
    <file name="u1982-4.png" crc="4173406413" ref="index"/>
    <file name="u1988-4.png" crc="3970561165" ref="index"/>
    <file name="u1994-4.png" crc="132010429" ref="index"/>
    <file name="u2000-4.png" crc="4268809048" ref="index"/>
    <file name="u2004-4.png" crc="261648224" ref="index"/>
    <file name="u2010-4.png" crc="498112964" ref="index"/>
    <file name="u2016-4.png" crc="421194813" ref="index"/>
    <file name="lili_reinhart_by_gage_skidmore-crop-u2022.jpg" crc="3862442872" ref="index"/>
    <file name="u2024-4.png" crc="435223889" ref="index"/>
    <file name="u2025-4.png" crc="4273612784" ref="index"/>
    <file name="hrh_prince_henry_of_wales-crop-u2044.jpg" crc="6960298" ref="index"/>
    <file name="u2046-4.png" crc="69186791" ref="index"/>
    <file name="u2047-4.png" crc="170312844" ref="index"/>
    <file name="sandra_von_ruffin_photo_emilio_esbardo-crop-u2076.jpg" crc="86767938" ref="index"/>
    <file name="u2078-4.png" crc="266363750" ref="index"/>
    <file name="u2075-4.png" crc="218765989" ref="index"/>
    <file name="cynthia_lawson_jaramillo_headshot_in_front_of_artwork-crop-u2103.jpg" crc="300393379" ref="index"/>
    <file name="u2105-4.png" crc="3785961228" ref="index"/>
    <file name="u2102-4.png" crc="35455607" ref="index"/>
    <file name="u2192-4.png" crc="65144663" ref="index"/>
    <file name="pexels-photo-415829-crop-u2224.jpg" crc="3827733386" ref="index"/>
    <file name="beautiful-2150881-crop-u2252.jpg" crc="37877143" ref="index"/>
    <file name="pexels-photo-428339-crop-u2264.jpg" crc="4022223110" ref="index"/>
    <file name="u2346-4.png" crc="147627076" ref="index"/>
    <file name="next-crop-u2276.png" crc="123138148" ref="index"/>
    <file name="back-crop-u2289.png" crc="296982679" ref="index"/>
    <file name="u2378-4.png" crc="267346747" ref="index"/>
    <file name="globes-1246245-crop-u2394.jpg" crc="184676181" ref="index"/>
    <file name="u2786-4.png" crc="4182289962" ref="index"/>
    <file name="u2560-4.png" crc="3811703392" ref="index"/>
    <file name="u2572-4.png" crc="298430521" ref="index"/>
    <file name="u2578-4.png" crc="3965776530" ref="index"/>
    <file name="u2584-4.png" crc="244005951" ref="index"/>
    <file name="u2590-4.png" crc="4250377280" ref="index"/>
    <file name="u2564-4.png" crc="505082449" ref="index"/>
    <file name="smartphone-crop-u2598.png" crc="35938202" ref="index"/>
    <file name="u2630-4.png" crc="3951151535" ref="index"/>
    <file name="mail-crop-u2612.png" crc="4229690209" ref="index"/>
    <file name="u2634-4.png" crc="299727143" ref="index"/>
    <file name="social-facebook-circular-button-crop-u2606.png" crc="3932587016" ref="index"/>
    <file name="pinterest-logo-crop-u2658.png" crc="432941682" ref="index"/>
    <file name="twitter-logo-button-crop-u2664.png" crc="468712546" ref="index"/>
    <file name="google-plus-social-logotype-crop-u2670.png" crc="120458733" ref="index"/>
    <file name="u2726-4.png" crc="4253004341" ref="index"/>
    <file name="u2728-4.png" crc="246893231" ref="index"/>
    <file name="u2729-4.png" crc="26668728" ref="index"/>
    <file name="u2725-4.png" crc="4173223484" ref="index"/>
    <file name="u2727-4.png" crc="27820879" ref="index"/>
    <file name="u2757-4.png" crc="68007468" ref="index"/>
    <file name="u2758-4.png" crc="305913920" ref="index"/>
    <file name="u2760-4.png" crc="248506646" ref="index"/>
    <file name="u2756-4.png" crc="37868201" ref="index"/>
    <file name="u2759-4.png" crc="4179897382" ref="index"/>
    <file name="u2499-7.png" crc="401408158" ref="index"/>
    <file name="u2501.png" crc="3818418719" ref="index"/>
    <file name="u2501-r.png" crc="4001115008" ref="index"/>
    <file name="u2501-m.png" crc="3874826137" ref="index"/>
    <file name="u2501-fs.png" crc="3846533738" ref="index"/>
    <file name="u2509-4.png" crc="4280145260" ref="index"/>
    <file name="u134.png" crc="4061649330" ref="index"/>
    <file name="u134-a.png" crc="366168916" ref="index"/>
    <file name="u187.png" crc="317436104" ref="index"/>
    <file name="u187-a.png" crc="4095047926" ref="index"/>
    <file name="u360.png" crc="205432870" ref="index"/>
    <file name="u360-a.png" crc="502873805" ref="index"/>
    <file name="u318.png" crc="141932410" ref="index"/>
    <file name="u318-a.png" crc="389621602" ref="index"/>
    <file name="u276.png" crc="486852773" ref="index"/>
    <file name="u276-a.png" crc="3911632141" ref="index"/>
    <file name="u234.png" crc="373520399" ref="index"/>
    <file name="u234-a.png" crc="195192254" ref="index"/>
    <file name="magnifier-tool.png" crc="485878346" seo="true" ref="index"/>
    <file name="children-1822474-crop-u5622.jpg" crc="4030366322" ref="index"/>
    <file name="u435-122.png" crc="4213011582" ref="index"/>
    <file name="back.png" crc="457712058" seo="true" ref="index"/>
    <file name="next.png" crc="345243508" seo="true" ref="index"/>
    <file name="books-1655783-crop-u6382.jpg" crc="3916080424" ref="index"/>
    <file name="play-button.png" crc="4156623473" seo="true" ref="index"/>
    <file name="u734-42.png" crc="198700920" ref="index"/>
    <file name="u738-42.png" crc="3918364347" ref="index"/>
    <file name="chalkboard-crop-u16412.jpg" crc="139232030" ref="index"/>
    <file name="books-2596809-crop-u10102.jpg" crc="3900839104" ref="index"/>
    <file name="u1080-42.png" crc="3967438145" ref="index"/>
    <file name="conference.png" crc="4084979162" seo="true" ref="index"/>
    <file name="u1121-62.png" crc="3772977562" ref="index"/>
    <file name="u1125-42.png" crc="253524846" ref="index"/>
    <file name="biology.png" crc="4026715048" seo="true" ref="index"/>
    <file name="u1185-62.png" crc="526508055" ref="index"/>
    <file name="u1184-42.png" crc="253524846" ref="index"/>
    <file name="lecture.png" crc="3941040025" seo="true" ref="index"/>
    <file name="u1220-62.png" crc="3947355724" ref="index"/>
    <file name="u1216-42.png" crc="253524846" ref="index"/>
    <file name="u1252-62.png" crc="169465823" ref="index"/>
    <file name="u1248-42.png" crc="253524846" ref="index"/>
    <file name="people-2557396-crop-u13472.jpg" crc="4217570824" ref="index"/>
    <file name="u1367-42.png" crc="332924705" ref="index"/>
    <file name="u1371-42.png" crc="4116587812" ref="index"/>
    <file name="coffee-2306471-crop-u15302.jpg" crc="113622340" ref="index"/>
    <file name="u1535-42.png" crc="3783633082" ref="index"/>
    <file name="u1534-42.png" crc="53110855" ref="index"/>
    <file name="library-849797-crop-u15822.jpg" crc="3965979466" ref="index"/>
    <file name="u1586-42.png" crc="3837577387" ref="index"/>
    <file name="u1585-42.png" crc="223778463" ref="index"/>
    <file name="u1307-42.png" crc="218649248" ref="index"/>
    <file name="left-arrow.png" crc="354740367" seo="true" ref="index"/>
    <file name="right-arrow.png" crc="168378035" seo="true" ref="index"/>
    <file name="knowledge-1052014-crop-u17882.jpg" crc="19863580" ref="index"/>
    <file name="u1808-42.png" crc="4220371636" ref="index"/>
    <file name="pexels-photo-428341-crop-u18902.jpg" crc="4077870167" ref="index"/>
    <file name="u1978-42.png" crc="3884702634" ref="index"/>
    <file name="u2000-42.png" crc="230378608" ref="index"/>
    <file name="lili_reinhart_by_gage_skidmore-crop-u20222.jpg" crc="306442431" ref="index"/>
    <file name="u2024-42.png" crc="4141977614" ref="index"/>
    <file name="u2025-42.png" crc="4274659069" ref="index"/>
    <file name="pexels-photo-220453-crop-u19062.jpg" crc="141992700" ref="index"/>
    <file name="u1982-42.png" crc="3970442545" ref="index"/>
    <file name="u2004-42.png" crc="3968688132" ref="index"/>
    <file name="hrh_prince_henry_of_wales-u2044.png" crc="184139290" ref="index"/>
    <file name="u2046-42.png" crc="308095343" ref="index"/>
    <file name="u2047-42.png" crc="293948364" ref="index"/>
    <file name="official_portrait_of_elizabeth_truss_crop_2-crop-u19182.jpg" crc="4134888261" ref="index"/>
    <file name="u1988-42.png" crc="4009362914" ref="index"/>
    <file name="u2010-42.png" crc="205518666" ref="index"/>
    <file name="sandra_von_ruffin_photo_emilio_esbardo-crop-u20762.jpg" crc="304310516" ref="index"/>
    <file name="u2078-42.png" crc="3914611243" ref="index"/>
    <file name="u2075-42.png" crc="404443421" ref="index"/>
    <file name="donald_pleasence_allan_warren_edit-crop-u19302.jpg" crc="103503055" ref="index"/>
    <file name="u1994-42.png" crc="4118548727" ref="index"/>
    <file name="u2016-42.png" crc="385115226" ref="index"/>
    <file name="cynthia_lawson_jaramillo_headshot_in_front_of_artwork-crop-u21032.jpg" crc="167718012" ref="index"/>
    <file name="u2105-42.png" crc="316634563" ref="index"/>
    <file name="u2102-42.png" crc="4227514367" ref="index"/>
    <file name="u2192-42.png" crc="3934182660" ref="index"/>
    <file name="back-crop-u22892.png" crc="3799728820" ref="index"/>
    <file name="pexels-photo-428339-crop-u22642.jpg" crc="211044806" ref="index"/>
    <file name="pexels-photo-415829-crop-u22242.jpg" crc="4153733320" ref="index"/>
    <file name="beautiful-2150881-crop-u22522.jpg" crc="4123459289" ref="index"/>
    <file name="next-crop-u22762.png" crc="466756459" ref="index"/>
    <file name="u2346-42.png" crc="247409535" ref="index"/>
    <file name="u2378-42.png" crc="4189872762" ref="index"/>
    <file name="u2510-4.png" crc="137533480" ref="index"/>
    <file name="smartphone.png" crc="3759629491" seo="true" ref="index"/>
    <file name="mail.png" crc="233316275" seo="true" ref="index"/>
    <file name="social-facebook-circular-button.png" crc="449869754" seo="true" ref="index"/>
    <file name="google-plus-social-logotype.png" crc="203637936" seo="true" ref="index"/>
    <file name="twitter-logo-button.png" crc="4257817881" seo="true" ref="index"/>
    <file name="pinterest-logo.png" crc="361166193" seo="true" ref="index"/>
  </folder>
  <file name="index.html" crc="41738290" seo="true" mt="1529816563798" redirect="true"/>
</manifest>